LICENSE
pydjantic/__init__.py
pydjantic/py.typed
pydjantic/pydjantic.py
pydjantic-1.1.5.dist-info/LICENSE
pydjantic-1.1.5.dist-info/METADATA
pydjantic-1.1.5.dist-info/WHEEL
pydjantic-1.1.5.dist-info/RECORD
