Metadata-Version: 2.1
Name: pydjantic
Version: 1.1.5
Summary: Pydantic Settings for Django
Home-page: https://github.com/ErhoSen/pydjantic
License: MIT
Keywords: pydantic,django,PydanticSettings,settings
Author: Vladimir Vyazovetskov
Author-email: erhosen@gmail.com
Requires-Python: >=3.8,<4.0
Classifier: Development Status :: 3 - Alpha
Classifier: Environment :: Other Environment
Classifier: Intended Audience :: Developers
Classifier: License :: OSI Approved :: MIT License
Classifier: Operating System :: OS Independent
Classifier: Programming Language :: Python :: 3
Classifier: Programming Language :: Python :: 3.8
Classifier: Programming Language :: Python :: 3.9
Classifier: Programming Language :: Python :: 3.10
Classifier: Programming Language :: Python :: 3.11
Classifier: Programming Language :: Python :: 3.12
Classifier: Topic :: Software Development :: Libraries :: Python Modules
Classifier: Typing :: Typed
Requires-Dist: dj-database-url (>=2.1.0)
Requires-Dist: pydantic (>=2.5.2)
Requires-Dist: pydantic-settings (>=2.1.0)
Project-URL: Repository, https://github.com/ErhoSen/pydjantic
